pydss/ResultData.py
pydss/SolveMode.py
pydss/__init__.py
pydss/common.py
pydss/config_data.py
pydss/controllers.py
pydss/dataset_buffer.py
pydss/dssBus.py
pydss/dssCircuit.py
pydss/dssElement.py
pydss/dssElementFactory.py
pydss/dssInstance.py
pydss/dssObjectBase.py
pydss/dssTransformer.py
pydss/element_fields.py
pydss/element_options.py
pydss/exceptions.py
pydss/export_list_reader.py
pydss/get_snapshot_timepoints.py
pydss/helics_interface.py
pydss/metrics.py
pydss/naerm.py
pydss/node_voltage_metrics.py
pydss/pyContrReader.py
pydss/pyDSS.py
pydss/pyResults.py
pydss/pydss_fs_interface.py
pydss/pydss_project.py
pydss/pydss_results.py
pydss/registry.py
pydss/simulation_input_models.py
pydss/storage_filters.py
pydss/thermal_metrics.py
pydss/unitDefinations.py
pydss/value_storage.py
pydss/Extensions/MonteCarlo.py
pydss/Extensions/__init__.py
pydss/ProfileManager/ProfileInterface.py
pydss/ProfileManager/__init__.py
pydss/ProfileManager/base_definitions.py
pydss/ProfileManager/common.py
pydss/ProfileManager/hooks/MongoDB.py
pydss/ProfileManager/hooks/__init__.py
pydss/ProfileManager/hooks/h5.py
pydss/api/__init__.py
pydss/api/endpoints.yaml
pydss/api/logging.yaml
pydss/api/server.py
pydss/api/schema/PyDSS.v1.json
pydss/api/schema/__init__.py
pydss/api/src/RunServer.bat
pydss/api/src/__init__.py
pydss/api/src/config.yaml
pydss/api/src/app/DataWriter.py
pydss/api/src/app/HDF5.py
pydss/api/src/app/JSON_writer.py
pydss/api/src/app/Tester.py
pydss/api/src/app/__init__.py
pydss/api/src/app/pydss.py
pydss/api/src/web/__init__.py
pydss/api/src/web/create_schema.py
pydss/api/src/web/handler.py
pydss/api/src/web/parser.py
pydss/apps/__init__.py
pydss/apps/data_viewer.py
pydss/cli/__init__.py
pydss/cli/add_post_process.py
pydss/cli/add_scenario.py
pydss/cli/controllers.py
pydss/cli/convert.py
pydss/cli/create_project.py
pydss/cli/edit_scenario.py
pydss/cli/export.py
pydss/cli/extract.py
pydss/cli/pydss.py
pydss/cli/reports.py
pydss/cli/run.py
pydss/cli/run_server.py
nrel_pydss-3.1.7.dist-info/METADATA
nrel_pydss-3.1.7.dist-info/WHEEL
nrel_pydss-3.1.7.dist-info/entry_points.txt
nrel_pydss-3.1.7.dist-info/licenses/LICENSE
nrel_pydss-3.1.7.dist-info/RECORD
